<?xml version="1.0" encoding="UTF-8"?>
<?xml-stylesheet type="text/xsl" href="https://rooneypower.github.io/sbct/xslt/program_style_pi.xsl"?>
<program xmlns:dc="http://purl.org/dc/elements/1.1/" xml:id="37">
   <metadata>
      <dc:title>Buddy: The Buddy Holly Story</dc:title>
      <dc:creator>South Bend Civic Theatre</dc:creator>
   </metadata>
   <text>
      <cover>
         <line>South Bend</line>
         <line>CIVIC THEATRE</line>
         <line>WINNER OF THE</line>
         <line>2007 LEIGHTON AWARD FOR NONPROFIT EXCELLENCE</line>
         <break/>
         <line>With UNDERWRITING by</line>
         <line>MFB, RIVERSIDE TERRACE, MAJORITY BUILDERS, HOLLADAY PROPERTIES,</line>
         <line>AND SELECT HEALTH NETWORK</line>
         <line>PRESENTS</line>
         <line>BY ARRANGEMENT WITH ALAN JANES FOR THEATRE PARTNERS PRODUCTIONS LTD, LONDON</line>
         <break/>
         <line>Buddy:</line>
         <line>THE BUDDY HOLLY STORY</line>
         <line>Written by ALAN JANES and ROB BETTINSON</line>
         <line>Originally Directed by ROB BETTINSON</line>
         <line>Directed For South Bend Civic Theatre by JEFF WILDER</line>
         <break/>
         <line>THE WILSON MAIN STAGE AUDITORIUM</line>
         <line>September 7-8-9, 13-14-15-16, 20-21-22-23, 2007</line>
         <break/>
      </cover>
      <crew>
         <header>THE PRODUCTION TEAM</header>
         <credit>
            <role>Director</role>
            <talent>Jeff Wilder</talent>
         </credit>
         <credit>
            <role>Assistant Director</role>
            <talent>Ben Little</talent>
         </credit>
         <credit>
            <role>Assistant to the Director</role>
            <talent>Beth Straub</talent>
         </credit>
         <credit>
            <role>Technical Directors</role>
            <talent>David Chudzynski &amp; Damen Mroczek</talent>
         </credit>
         <credit>
            <role>Music Director</role>
            <talent>Jack Pavlekovich</talent>
         </credit>
         <credit>
            <role>Stage Manager</role>
            <talent>Tammy Pavlekovich</talent>
         </credit>
         <credit>
            <role>Set Design</role>
            <talent>Damen Mroczek</talent>
         </credit>
         <credit>
            <role>Lighting Design</role>
            <talent>David Chudzynski</talent>
         </credit>
         <credit>
            <role>Light Operator</role>
            <talent>Bill Kennedy</talent>
         </credit>
         <credit>
            <role>Sound Operator</role>
            <talent>Jeff Wilder</talent>
         </credit>
         <credit>
            <role>Audio Support</role>
            <talent>Jim Paczesny</talent>
         </credit>
         <credit>
            <role>Costume Design</role>
            <talent>Jonnie Kilic</talent>
         </credit>
         <credit>
            <role>Costume Assistant</role>
            <talent>Seyhan Kilic</talent>
         </credit>
         <credit>
            <role>Costume Apprentice Taylor</role>
            <talent>Renee Wilder</talent>
         </credit>
         <credit>
            <role>Set</role>
            <talent>Crew Cast</talent>
         </credit>
         <credit>
            <role>Set Construction &amp; Painting</role>
            <talent>David Chudzynski, Matt Davidson, Damen Mroczek, Meg Robenalt, Jody Thorla, Dana Vagg, John Wiley</talent>
         </credit>
      </crew>
      <cast>
         <header>THE CAST</header>
         <credit>
            <role>The Hayriders</role>
            <talent>Richard E. Bliley, April Szymanski, Kyle Curtis, Tim Jester</talent>
         </credit>
         <credit>
            <role>Buddy Holly</role>
            <talent>Billy McGuigan</talent>
         </credit>
         <credit>
            <role>Joe B.</role>
            <talent>Mauldin Jim Paczesny</talent>
         </credit>
         <credit>
            <role>Jerry Allison</role>
            <talent>Troy McKee</talent>
         </credit>
         <credit>
            <role>Teeny Boppers</role>
            <talent>Kyle Curtis, April Szymanski, Amanda Gonzalez, Dana Vagg, Taylor Renee Wilder, Seyhan Kilic</talent>
         </credit>
         <credit>
            <role>Hipockets Duncan</role>
            <talent>Anthony Panzica</talent>
         </credit>
         <credit>
            <role>Decca Producer</role>
            <talent>Jack Pavlekovich</talent>
         </credit>
         <credit>
            <role>Tommy (the Fourth Cricket)</role>
            <talent>Tim Jester</talent>
         </credit>
         <credit>
            <role>Norman Petty</role>
            <talent>Kyle Curtis</talent>
         </credit>
         <credit>
            <role>Vi Petty</role>
            <talent>Seyhan Kilic</talent>
         </credit>
         <credit>
            <role>New York</role>
            <talent>D.J. Richard E. Bliley</talent>
         </credit>
         <credit>
            <role>Apollo Performers</role>
            <talent>Tabitha Lee, Ben Little, Rod Todd</talent>
         </credit>
         <credit>
            <role>Maria Elena</role>
            <talent>Dana Vagg</talent>
         </credit>
         <credit>
            <role>Murray Deutch</role>
            <talent>Paul Frye</talent>
         </credit>
         <credit>
            <role>Shirley</role>
            <talent>Amanda Gonzalez</talent>
         </credit>
         <credit>
            <role>J.P. Richardson (The Big</role>
            <talent>Bopper) Jack Pavlekovich</talent>
         </credit>
         <credit>
            <role>Clear Lake Emcee</role>
            <talent>Paul Frye</talent>
         </credit>
         <credit>
            <role>Ritchie Valens</role>
            <talent>Michael Cripe*</talent>
         </credit>
         <credit>
            <role>Clear Lake Singers</role>
            <talent>Ben Little, Anthony Panzica,</talent>
         </credit>
         <credit>
            <role/>
            <talent>Rod Todd, Jim Paczesny, Dana Vagg,</talent>
         </credit>
         <credit>
            <role/>
            <talent>April Szymanski, Tabitha Lee,</talent>
         </credit>
         <credit>
            <role/>
            <talent>Seyhan Kilic, Amanda Gonzalez</talent>
         </credit>
      </cast>
      <setting>
         <header>SETTING</header>
         <line>Lubbock, Texas; Nashville, Tennessee; Clovis, New Mexico;</line>
         <line>New York City; and Clear Lake, Iowa; between January 1956</line>
         <line>and February 3, 1959 (the day the music died)</line>
         <break/>
         <line>MUSTCAL CREDITS</line>
         <line>The use of the songs in this production is by arrangement with:</line>
         <line>'Flower Of My Heart' Holly House Inc.</line>
         <line>'Ready Teddy' Unichappell Music Inc.</line>
         <line>'Blue Days Black Nights' Unichappell Music Inc.</line>
         <line>'That's All Right' Unichappell Music Inc.</line>
         <line>'A Teenager In Love' Unichappell Music Inc.</line>
         <line>'That'll Be The Day' MPL Comm. Inc. MPL/Wren</line>
         <line>'Peggy Sue' MPL Comm. Inc. MPL/Wren</line>
         <line>'Maybe Baby' MPL Comm. Inc. MPL/Wren</line>
         <line>'Not Fade Away' MPL Comm. Inc. MPL/Wren</line>
         <line>'True Love Ways' MPL Comm. Inc. MPL/Wren</line>
         <line>'Looking For Someone To Love' MPL Comm. Inc. MPL/Wren</line>
         <line>'Listen To Me' MPL Comm. Inc. MPL/Wren</line>
         <line>'It's So Easy To Fall Jn Love' MPL Comm. Inc. MPL/Wren</line>
         <line>'Well Alright' MPL Comm. Inc. MPL/Wren</line>
         <line>'When You Ask About Love' Acuff Rose Music Inc.</line>
         <line>'Words of Love' MPL Comm. Inc.</line>
         <line>'Oh Boy' Wren Music Co. c/o MPL</line>
         <line>'Rave On' Wren Music Co. c/o MPL</line>
         <line>'Heartbeat' Wren Music Co. c/o MPL</line>
         <line>'Changing All Those' Cedarwood Publishing Co.</line>
         <line>'Think It Over' Cedarwood Publishing Co./Southern Music Publishing Co.</line>
         <line>'Everyday' Southern Music Publishing Co.</line>
         <line>'Mailman Bring Me No More' Southern Music Publishing Co./ Beinstock Publishing</line>
         <line>'Peggy Sue Got Married' Southern Music Publishing Co.</line>
         <line>'Why Do Fools' Windswept Pacific Ent.</line>
         <line>'Chantilly Lace' Donald Daily, Glad Music Co./ Fort Knox Music Inc./ Trio Music Company Inc.</line>
         <line>'Raining In My Heart' House of Bryant Pubs. Inc.</line>
         <line>'It Doesn't Matter Anymore' Management Agency</line>
         <line>'Johnny B Goode' Isalee Music Co.</line>
         <line>'Rock Around With Ollie Vee' Hill and Range Songs Inc.</line>
         <line>All other songs, arrangements and incidental music by Paul Jury</line>
      </setting>
      <bios>
         <header>WHO'S WHO</header>
         <entry>RICHARD E. BLILEY (Hayrider, New York DJ) returns to theatre after tour­ing for many years as a musician with such bands as The Four Horsemen, Del Sigma Five, Peppermint Riot. and Doc Cricket. He recorded with Bobby Darin at Roulette Records in New York. He currently plays bass guitar and provides back-up vocals for the band Chantilly Lace. Before touring, he had been directed by James Lewis Casaday, performed with Pres Players and with Country Playhouse. He welcomes the chance to perform on stage with SBCT.</entry>
         <entry>DAVID CHUDZYNSKI (Technical Director) is the first full-time, salaried Technical Director in the history of South Bend Civic Theatre. He is an accomplished actor, stage director, playwright, and theatre instructor, as well.</entry>
         <entry>MICHAEL CRIPE (Ritchie Valens, Understudy for Buddy) may be remem­bered by SBCT audiences as Max in last year's production of The Sound of Music at The Morris Performing Arts Center. A proud and long-standing member of Actor's Equity Association, Michael has worked in professional theatre for the past 30 years, most recently cast as a principal opposite Julie Andrews in the original Broadway production of Victor/Victoria. Michael will next be directing Smoke on the Water for Elkhart Civic Theatre.</entry>
         <entry>KYLE CURTIS (Norman Petty, Hayrider, Teeny Bopper) is appearing in his fourth SBCT production, last having been seen in Zombies From the Beyond. He is extremely excited to be involved with BUDDY and would like to thank the entire company for the experience. Thanks also to all of his friends and family for their constant support. "I love you all so much!"</entry>
         <entry>PAUL FRYE (Murray Deutch, Clear Lake Emcee) debuted on stage in SBCT's production of1/uck Finn in March, but can regularly be seen ushering at South Bend Civic productions. He would like to thank all his friends for their "understanding and tolerance with his summer-long Saturday yard sales."</entry>
         <entry>AMANDA GONZALES (Shirley, Teeny Bopper, Clear Lake Singer) has been involved with theatre since the age of 8, most recently in SBCT's Disney's High School Musical. Previously seen _in The Adventures of Huck Finn and The Sound of Music, she wishes to thank her family for their love and support.</entry>
         <entry>TIM JESTER (Tommy, Hayrider, Teeny Bopper) was led to his first production with SBCT by his lifelong fascination with Rock and Blues. Previous acting credits include: Carousel, Finian 's Rainbow, Guys &amp; Dolls, and Toni. Tim is a local guitarist, playing with various bands. He wishes to thank his family (especially his morn for his first guitar), friends, and "especially, Jeff" who convinced him he COULD play this part!</entry>
         <entry>Mrs. ORHAN (JONNIE) KILIC (Costumes) has served on the board of directors of SBGT. as well as the Play Selection and Long Range Planning Committees. She has directed five shows for Civic and has costumed for the theatre since 1989. She says she is excited to be overseeing the organization of the SBCT's new costume shop.</entry>
         <entry>SEYHAN KILIC (Vi Petty, Teeny Bopper. Clear Lake Singer), a veteran actor, director, and volunteer with SBCT, is currently the drama director at Trinity UMC in Elkhart. She has volunteered in various capacities with South Bend Civic for over fifteen years and has "enjoyed every minute of it." Holding a B.A. in theatre from MSU, she is currently seeking her Music Teaching License from Bethel College.</entry>
         <entry>TABITHA LEE (Apollo Performer, Clear Lake Singer) was recently seen at SBCT in Zombies from the Beyond. Previous credits include Mrs. Bob Crachit's Wild Christ­mas Binge at SBCT, as well as the lead role in Adam and Eve with Beckwith Theatre in Dowagiac. She plans to "continue her path in theatre and the performing arts."</entry>
         <entry>BEN LITTLE (Asst. Director, Apollo Pcrfom1er, Clear Lake Singer) is no stranger to SBCT. Past productions include Smokey Joe's Cafe, Six Degrees of Separation, Noises Off, and The World Goes 'Round, to name just a few. Ben returns rockin' and rollin' and dedicates this show to his wife, Lisa, the kids, and the SBCT audience! So, brothers and sisters, come join the party! Let's rock 'n' roll!! Oh yeahhhhhhh!!!</entry>
         <entry>His interpretation of Buddy Holly has taken BILLY McGUIGAN (Buddy Holly) all over the United States. He has appeared in over 300 performances of BUDDY: The Buddy Holly Story in the past five years to critical acclaim. Billy's performance in this show has also led to incredible box-office successes wherever he has performed. The Omaha Community Playhouse (2002), The Des Moines Playhouse (2003), and The Albuquerque Little Theatre (2004) all report Buddy as their No. 1 show in terms of attendance and ticket sales. Billy's performance at the Broadway Palm Theatre (2005) in Mesa, AZ, garnered a Spotlight Award for Best Actor in a Musical and a nomination for an "Arizoni" Award for Actor in a Major Musical Role. Recently, the writers and producers of BUDDY chose Billy as their "Preferred Buddy Holly" in the United States. Billy also wrote and co­produced Rave On!, which has played all over the U.S., has been performed with symphony orchestras, and is one of two "tribute" shows endorsed by the Buddy Holly Estate. Rave On! also generated three highly successful CDs: "Rave On! Live at the Drew!," "Rave On!: Live" and "Rave On!: Sessions," which are available at all performances. In July 2006, Billy released an album of original music, entitled "Billy As Billy." When not on the road, Billy lives in Omaha with his beautiful wife, Rachelle, and their amazing daughter, Cartney.</entry>
         <entry>TROY McKEE (Drums) traces his musical roots back at least three generations, starting with his great-great-grandfather, Cheatem. Troy began piano lessons at age 7 and got his first drum kit at age 8 and first guitar at 13. A life-long love of all things "music" and "playing in bands" led Troy to audition for BUDDY. .. and the "rest will just be Rock 'n' Roll!"</entry>
         <entry>JIM PACZENY (Joe B Mauldin, Clear Lake Singer) is a Mishawaka native, making his SBCT debut. An accomplished musician, Jim has held the stage across the U.S. with various bands, but this marks his first acting endeavor. He looks forward to working with SBCT in the future.</entry>
         <entry>ANTHONY PANZICA (Hipockets Duncan, Understudy for Ritchie Valens, Clear Lake Singer) notes that BUDDY is his fourth SBCT production, but his first "musical." "l feel so fortunate to have the opportunity to pursue such a creative endeavor, as life on stage encompasses all the arts." He wishes to thank all those who made work, family, and monetary sacrifices to make this show a reality. "Thanks for all your support and dedication! Enjoy the show!"</entry>
         <entry>JACK PAVLEKOVICH (The Big Bopper, Decca Producer, Musical Director), originally from Milwaukee, is a founding member of the regional act Chantilly Lace. He has toured as an opening act or back-up for such bands as Blood, Sweat and Tears, Jan and Dean, Rare Earth, and Peter Noone (of Herman's Hermits), to name just a few. This production holds a special place in Jack's heart, having toured with the original Crickets, with whom he continues to correspond. Jack played for SBCT's 2006 production of Always ... Patsy Cline, and was musical director for the Not Quite Professional Theatre Company's recent production of Godspell. He dedicates this performance to his lovely wife, Tammy, and their two daughters. Ashlee and Jamie. "Thanks for letting me a part of this great show!"</entry>
         <entry>TAMMY PAVLEKOVICH (Stage Manager), an accomplished musician since the age of six, plays the American Standard and French flute. A member of the South Bend Youth Symphony, as well as the South Bend Symphony, Tammy has graced the stage as an actress and musician. She would like to thank her husband, Jack, and daughters Aimee and Ashlee, for their "love, patience and support."</entry>
         <entry>BETH STAUB (Asst. to the Dir., Understudy for Vi) previously assisted Jeff with his production of Jesus Christ Superstar but BUDDY marks her first production with SBCT. Beth dedicates her work to her daughter and thanks her family and friends for all of their love and supp011.</entry>
         <entry>APRIL SZYMANSKI (Hayrider, Teeny Bopper, Clear Lake Singer), a senior at Washington High School, has been seen in productions of The Bear, The Man Who Came to Dinner, and, most recently, in SBCSC's production of Disney's Beauty &amp; the Beast. She plans to pursue an acting career by attending IUSB next year and hopes to participate in more SBCT productions in the future.</entry>
         <entry>ROD TODD (Apollo Performer, Clear Lake Singer) was seen most recently in SBCT's production of Fences and, before that, in A Lesson Before Dying, Force Continuum, Black Coffee, Wit, and A Raisin in the Sun, among others.</entry>
         <entry>DANA VAGG (Maria Elena, Teeny Bopper, Clear Lake Singer) has played major acting roles since 1996 in SBCT productions of Blue Window, A Streetcar Named Desire, Still Life With Iris, Enchanted April, Black Coffee, Proof, Light Up the Sky, and others. A student twice at the Royal Academy of Dramatic Arts in London, Dana has worked as a teaching artist for several years in SBCT's theatre workshops for youth.</entry>
         <entry>DONALD WANJIKU-KWIATKOWSKI (Piano/Keyboards) has played piano since the age of six and has perfom1ed with such bands as Reproduction, Soul Sounds, and In the Pocket. He is pleased to be making his SBCT debut in BUDDY!</entry>
         <entry>JEFF WILDER (Director) has directed and performed previously in SBCT pro­ductions of Smokey Joe's Cafe, The World Goes 'Round, and the 2006 hit, Always . .. Patsy Cline, to name just a few. Jeff wishes to thank Jack "for talking him into directing this show in the first place," and this "fantastic cast and band! You guys ROCK!!" Most importantly, he wishes to thank his wife and family for "sticking by him through this show and every other one, too!"</entry>
         <entry>TAYLOR RENEE WILDER (Teeny Bopper). as part of a "theatre family," has been actively involved with productions since the age of nine. Her debut performance was in Baby, That's Rock 'n' Roll. She has also appeared in SBCT's The World Goes 'Round and Curtain Up! Theatricals' Jesus Christ Superstar. She would like to thank her mom, dad, and family for their support.</entry>
         <entry>AN UPDATE ON The South Bend Civic Wilson Society</entry>
         <entry>Following on the heels of one of the most ambitious building campaigns in the history of American commw1ity theatre, South Bend Civic Theatre is proud to announce the first members to join SBCT's Wilson Society, a select group of donors dedicated to securing with endowment gifts of $5,000 or more the theatre's health and prosperity for the next 50 years and beyond. They are: Gene &amp; Jane Bruce Alfred H. &amp; Martha J. Choitz Leslie J. Choitz Dick &amp; Chris Currey Tom &amp; Cathy Lower Alex &amp; Pam Regnery Barbara K. Warner Marjorie H. Wilson</entry>
      </bios>
   </text>
</program>
