<?xml version="1.0" encoding="UTF-8"?>
<?xml-stylesheet type="text/xsl" href="https://rooneypower.github.io/sbct/xslt/program_style_pi.xsl"?>
<program xmlns:dc="http://purl.org/dc/elements/1.1/" xml:id="47">
   <metadata>
      <dc:title>Sticks and Bones</dc:title>
      <dc:creator>South Bend Civic Theatre</dc:creator>
   </metadata>
   <text>
      <cover>
         <line>South Bend</line>
         <line>CIVIC THEATRE</line>
         <line>Full Season Sponsor, Villing &amp; Co.</line>
         <line>Studio Sponsor, Community Foundation of St. Joseph County</line>
         <break/>
         <line>Proudly Present:</line>
         <break/>
         <line type="playTitle">Sticks and Bones</line>
         <line>Written by David Rabe</line>
         <line>Directed by Scott Jackson</line>
         <line>March 30, 31, April 6, 7 at 8 PM; April 4, 5 at 7:30 PM,</line>
         <line>April 1 at 3:00 PM</line>
         <line>Warner Studio Theatre</line>
         <break/>
         <line>Produced by special arrangement with Samuel French, Inc.</line>
         <break/>
         <line>SBCT fundded in part through a grant from Indiana Arts Commission &amp; National Endowment for the Arts</line>
         <break/>
         <line>With gratitude to the Community Foundation of South Bend for administering IAC funds, managing SBCT's endowment and for group marketing opportunities through the Arts Everywhere.com initiative.</line>
      </cover>
      <cast>
         <header>The Cast</header>
         <credit>
            <role>Ozzie</role>
            <talent>Paul J. Hanft</talent>
         </credit>
         <credit>
            <role>Harriet</role>
            <talent>Melissa Gard</talent>
         </credit>
         <credit>
            <role>David</role>
            <talent>Jason L. Clark</talent>
         </credit>
         <credit>
            <role>Ricky</role>
            <talent>Richard Isacson</talent>
         </credit>
         <credit>
            <role>Father Donald</role>
            <talent>Brad Mazick</talent>
         </credit>
         <credit>
            <role>Sgt Major</role>
            <talent>Charlie Florance</talent>
         </credit>
         <credit>
            <role>Zung</role>
            <talent>Amorena Ruffolo</talent>
         </credit>
      </cast>
      <crew>
         <header>The Production Team</header>
         <credit>
            <role>Director/Sound Design</role>
            <talent>Scott Jackson</talent>
         </credit>
         <credit>
            <role>Stage Manager</role>
            <talent>Jody Thorla</talent>
         </credit>
         <credit>
            <role>Set Design</role>
            <talent>Jacee Rohlck</talent>
         </credit>
         <credit>
            <role>Lighting Design</role>
            <talent>Doug Hildeman</talent>
         </credit>
         <credit>
            <role>Costumes Lois Veen Donald</role>
            <talent>Eugene Willman</talent>
         </credit>
         <credit>
            <role>Projection Design</role>
            <talent>Kevin Krizmanich</talent>
         </credit>
         <credit>
            <role>Props/Stage Crew</role>
            <talent>Teri Szynski</talent>
         </credit>
         <credit>
            <role>Space Configuration</role>
            <talent>Scott Jackson, Cast</talent>
         </credit>
         <credit>
            <role>Production Photography</role>
            <talent>Jon Gilchrist</talent>
         </credit>
         <credit>
            <role>Light Operator</role>
            <talent>Sandra Childress</talent>
         </credit>
         <credit>
            <role>Sound/Projection Operator</role>
            <talent>Jason Holderread</talent>
         </credit>
      </crew>
      <setting>
         <header>Time: 1968</header>
         <line>Setting: The Family Home</line>
         <line>Will be performed with one intermission.</line>
         <break/>
         <line>Please turn off all cell phones, cameras and electronic devices.</line>
         <line>Thank you.</line>
      </setting>
      <bios>
         <header>WHO'S WHO IN THE CAST &amp; CREATIVE TEAM</header>
         <entry>Jason L. Clark (David) hails from the University of Northern Colorado, and is proud to be making his debut performance here at SBCT. Past credits include: You Can't Take It With You, Flags, The Elephant Man, True West, A Skull In Connemara, Twelfth Night, The Merchant of Venice, Bug, Amadeus and The Play About The Baby. "Thanks to Scott and the rest of this amazing cast and crew for this great and fulfilling experience."</entry>
         <entry>Charles Florance (Sgt. Major) is making his first production with SBCT. He dedicates this, and all things, to his wife, Tina Florance.</entry>
         <entry>Melissa Gard (Harriet) is a veteran of stage, film and radio in the South Bend area. Although she did many shows with SBCT in the "old days", her last appearance at was in Body of Water. Since then, she has worked with New World Arts in Goshen in Who's Afraid o/Virginia Woolf and boom. She is an original member of the Acting Ensemble, having appeared in various shows (most recently in Beasley's Christmas Party) and staged readings. She is pleased and proud to be working with the case and crew of Sticks and Bones, and has learned to ask herself, when in doubt..."What Would Zung Do?"</entry>
         <entry>Paul J. Hanft (Ozzie) is making his debut at SBCT; he has performed at Premier Arts in Elkhart, New World Arts in Goshen, Elkhart Civic Theatre, Kalamazoo Civic Theatre and The Notre Dame Shakespeare Festival. Favorite productions include Officer Lockscock in Urinetown, Escanaba in the Moonlight, Moon Over Buffalo, I Hate Hamlet, My Three Angels, Man Of La Mancha and A Christmas Carol. Paul would like to dedicate his performance to "everyone in the audience who actually watched Ozzie, Harriet, David and Ricky on Television."</entry>
         <entry>Richard Isacson (Ricky) is in his second SBCT production, after lase year's Strangers on a Train. He is from Muskegon, MI, graduated from Muskegon Community College performing there in It's A Wonderful Life: A Live Radio Play and Rosencrantz and Guildenstern Are Dead and was Assistant Director for The Pillowman. "I am very happy to be a pare of such a great play, with a wonderful cast."</entry>
         <entry>Scott Jackson (Director) is the Executive Director of Shakespeare at Notre Dame having previously served as Executive Director for the Fairbanks Shakespeare Theatre in Fairbanks, Alaska. He holds a BA in Theatre from Indiana University/Bloomington, as well as intensive study in acting at the London Centre for Theatre Studies. Since relocating co South Bend in 2007 he has been seen as Lee in the SBCT's True West, Touchstone in the Notre Dame Shakespeare Festival's production of As You Like It, as well as Guy Montag in Fahrenheit 451 and Nick in last season's Who's Afraid of Virginia Woolf at New World Arts. His most recent directing credits include Peter Sinn Nachtrieb's boom at New World Arts and a "virtual" staging of David Henry Hwang's The Sound of a Voice in the Discovery Lab of the Arctic Research Supercomputing Center at the University of Alaska/Fairbanks.</entry>
         <entry>Brad Mazick (Father Donald) is a psychologist playing a priest who thinks he is a psychiatrist. It has been disorienting at times but a wonderful experience. Though he has done other community theatre, this is his first SBCT production and appreciates the opportunity. He thanks his children, Danni, Bree, Will and his girlfriend, Kristina, for their patience and support.</entry>
         <entry>Amorena Ruffolo (Zung) is a graduate of IUSB with a BFA in Theatre and a Minor in Dance. She appeared with SBCT in A Little Princess. IUSB credits include A Raisin in the Sun, A Midsummer Night's Dream, West Side Story, Alice in Wonderland. Other acting credits include And Then They Came for Me with Acting Ensemble; A Bad Year for Tomatoes with Barn Swallow Community Theatre. She would like thank her family and close friends that have always been supportive of her career.</entry>
         <entry>Jody Thorla (Stage Manager) "would like to thank the cast and production crew for making this engaging and surreal story come to life (that is definitely a compliment). He would also like to thank you, the patron, for your support and allowing us to present this intense and relevant story of the effects of war and the human condition. Peace."</entry>
         <entry>Up Next at SBCT:</entry>
         <entry>Gypsy April 27-May 13 Wilson Mainstage Auditorium</entry>
         <entry>Superior Donuts June 1-10 Warner Studio Theatre</entry>
         <entry>Anna in the Tropics June 22-July 1 Wilson Mainstage Auditorium</entry>
      </bios>
   </text>
</program>
